tirikchilik/__init__.py
tirikchilik/tirikchilik.py
tirikchilik-0.0.1.dist-info/METADATA
tirikchilik-0.0.1.dist-info/WHEEL
tirikchilik-0.0.1.dist-info/top_level.txt
tirikchilik-0.0.1.dist-info/RECORD
