Metadata-Version: 2.1
Name: tirikchilik
Version: 0.0.1
Summary: An unofficial Python wrapper for Tirikchilik API.
Home-page: https://github.com/Diyarbekoralbaev/tirikchilik
Author: Diyarbek Oralbaev
Author-email: diyarbekdev@gmail.com
License: MIT
Classifier: License :: OSI Approved :: MIT License
Classifier: Programming Language :: Python
Classifier: Programming Language :: Python :: 3
Classifier: Programming Language :: Python :: 3.6
Classifier: Programming Language :: Python :: 3.7
Classifier: Programming Language :: Python :: 3.8
Classifier: Programming Language :: Python :: 3.9
Classifier: Programming Language :: Python :: 3.10
Classifier: Programming Language :: Python :: 3.11
Classifier: Programming Language :: Python :: 3.12
Classifier: Programming Language :: Python :: Implementation :: CPython
Classifier: Programming Language :: Python :: Implementation :: PyPy
Classifier: Development Status :: 3 - Alpha
Classifier: Operating System :: OS Independent
Classifier: Topic :: Software Development :: Libraries
Classifier: Intended Audience :: Developers
Requires-Python: >=3.9
Requires-Dist: requests~=2.32.3
Requires-Dist: urllib3~=2.2.3
